pyramid_persona/utils.py
pyramid_persona/tests.py
pyramid_persona/views.py
pyramid_persona/__init__.py
pyramid_persona/templates/forbidden.html
pyramid_persona/templates/persona.js
pyramid_persona-1.6.1.dist-info/RECORD
pyramid_persona-1.6.1.dist-info/METADATA
pyramid_persona-1.6.1.dist-info/top_level.txt
pyramid_persona-1.6.1.dist-info/metadata.json
pyramid_persona-1.6.1.dist-info/DESCRIPTION.rst
pyramid_persona-1.6.1.dist-info/WHEEL
