Metadata-Version: 2.0
Name: pyramid-persona
Version: 1.6.1
Summary: pyramid_persona
Home-page: https://github.com/madjar/pyramid_persona
Author: Georges Dubus
Author-email: georges.dubus@gmail.com
License: UNKNOWN
Keywords: web pyramid pylons authentication persona
Platform: UNKNOWN
Classifier: Programming Language :: Python
Classifier: Programming Language :: Python :: 2
Classifier: Programming Language :: Python :: 3
Classifier: Framework :: Pyramid
Classifier: Topic :: Internet :: WWW/HTTP
Requires-Dist: pyramid (>=1.4)
Requires-Dist: PyBrowserID
Requires-Dist: requests (>=1.0)
Requires-Dist: MarkupSafe
